{
    "users": [
        {
            "id": 0,
            "name": "John Doe",
            "work": "Google",
            "email": "john.doe@gmail.com",
            "age": 26,
            "address": "83 warner street",
            "city": "boston",
            "enable": true
        },
        {
            "id": 1,
            "name": "Nilesh Luharia",
            "work": "Google",
            "age": 26,
            "email": "nilesh.luharia@gmail.com",
            "address": "86 warner street",
            "city": "boston",
            "enable": true
        },
        {
            "id": 2,
            "name": "Saryu Luhar",
            "work": "Google",
            "age": 26,
            "email": "saryu.luhar@gmail.com",
            "address": "84 warner street",
            "city": "boston",
            "enable": true
        }
    ]
}